README.md
setup.cfg
setup.py
arbitrium/__init__.py
arbitrium/menu.py
arbitrium.egg-info/PKG-INFO
arbitrium.egg-info/SOURCES.txt
arbitrium.egg-info/dependency_links.txt
arbitrium.egg-info/top_level.txt