Metadata-Version: 1.1
Name: arbitrium
Version: 1.1.4
Summary: Arbitrium - The Easy Menu System For Python
Home-page: https://github.com/bentechy66/arbitrium
Author: Ben Griffiths
Author-email: sendbenspam@yahoo.co.uk
License: MIT
Download-URL: https://github.com/bentechy66/arbitrium/archive/v_01.tar.gz
Keywords: MENU,EASY,BEGINNER-FRIENDLY
Platform: UNKNOWN
Classifier: Development Status :: 3 - Alpha
Classifier: Intended Audience :: Developers
Classifier: Topic :: Software Development :: Build Tools
Classifier: License :: OSI Approved :: MIT License
Classifier: Programming Language :: Python :: 3.5
Classifier: Programming Language :: Python :: 3.6
Classifier: Programming Language :: Python :: 3.7
